commit_message_cli/__init__.py
commit_message_cli/cli.py
commit_message_cli-1.0.7.dist-info/METADATA
commit_message_cli-1.0.7.dist-info/WHEEL
commit_message_cli-1.0.7.dist-info/entry_points.txt
commit_message_cli-1.0.7.dist-info/RECORD
