Metadata-Version: 2.1
Name: commit-message-cli
Version: 1.0.7
Summary: CLI tool to generate commit messages using AI
Home-page: https://github.com/smoothdev-io/commit-message-cli
License: MIT
Keywords: git,commit,ai,cli
Author: Brendan Putek
Author-email: brendan.putek@smoothdev.io
Requires-Python: >=3.12,<4.0
Classifier: License :: OSI Approved :: MIT License
Classifier: Programming Language :: Python :: 3
Classifier: Programming Language :: Python :: 3.12
Classifier: Programming Language :: Python :: 3.13
Requires-Dist: requests (>=2.31.0,<3.0.0)
Project-URL: Repository, https://github.com/smoothdev-io/commit-message-cli
